{
  "minecraft:recipes/tools/flint_and_steel": {
    "criteria": {
      "has_obsidian": "2021-01-11 16:51:14 -0300"
    },
    "done": true
  },
  "minecraft:recipes/transportation/acacia_boat": {
    "criteria": {
      "in_water": "2021-01-11 16:53:12 -0300"
    },
    "done": true
  },
  "minecraft:recipes/transportation/oak_boat": {
    "criteria": {
      "in_water": "2021-01-11 16:53:12 -0300"
    },
    "done": true
  },
  "minecraft:recipes/misc/emerald": {
    "criteria": {
      "has_emerald_block": "2021-01-11 16:50:54 -0300"
    },
    "done": true
  },
  "minecraft:recipes/transportation/dark_oak_boat": {
    "criteria": {
      "in_water": "2021-01-11 16:53:12 -0300"
    },
    "done": true
  },
  "minecraft:recipes/transportation/birch_boat": {
    "criteria": {
      "in_water": "2021-01-11 16:53:12 -0300"
    },
    "done": true
  },
  "minecraft:story/form_obsidian": {
    "criteria": {
      "obsidian": "2021-01-11 16:51:14 -0300"
    },
    "done": true
  },
  "minecraft:recipes/transportation/jungle_boat": {
    "criteria": {
      "in_water": "2021-01-11 16:53:12 -0300"
    },
    "done": true
  },
  "minecraft:recipes/transportation/spruce_boat": {
    "criteria": {
      "in_water": "2021-01-11 16:53:12 -0300"
    },
    "done": true
  },
  "minecraft:recipes/decorations/enchanting_table": {
    "criteria": {
      "has_obsidian": "2021-01-11 16:51:14 -0300"
    },
    "done": true
  },
  "minecraft:adventure/adventuring_time": {
    "criteria": {
      "minecraft:beach": "2021-01-11 16:53:20 -0300",
      "minecraft:dark_forest": "2021-01-11 16:53:27 -0300",
      "minecraft:river": "2021-01-11 16:53:12 -0300",
      "minecraft:wooded_hills": "2021-01-11 16:48:54 -0300",
      "minecraft:plains": "2021-01-11 01:04:03 -0300"
    },
    "done": false
  },
  "DataVersion": 2584
}